forum_analyzer/__init__.py
forum_analyzer/cli.py
forum_analyzer/analyzer/__init__.py
forum_analyzer/analyzer/llm_analyzer.py
forum_analyzer/analyzer/reporter.py
forum_analyzer/collector/__init__.py
forum_analyzer/collector/api_client.py
forum_analyzer/collector/checkpoint_manager.py
forum_analyzer/collector/models.py
forum_analyzer/collector/orchestrator.py
forum_analyzer/config/__init__.py
forum_analyzer/config/settings.py
forum_analyzer-0.1.0.dist-info/licenses/LICENSE
forum_analyzer-0.1.0.dist-info/METADATA
forum_analyzer-0.1.0.dist-info/WHEEL
forum_analyzer-0.1.0.dist-info/entry_points.txt
forum_analyzer-0.1.0.dist-info/top_level.txt
forum_analyzer-0.1.0.dist-info/RECORD
