Metadata-Version: 2.4
Name: forum-analyzer
Version: 0.1.0
Summary: Shopify Developer Forum Analyzer
Author-email: Phil Leggetter <phil@leggetter.co.uk>
License-Expression: MIT
Project-URL: Homepage, https://github.com/leggetter/discourse-forum-analyzer
Project-URL: Repository, https://github.com/leggetter/discourse-forum-analyzer
Keywords: shopify,forum,analyzer,discourse
Classifier: Development Status :: 3 - Alpha
Classifier: Intended Audience :: Developers
Classifier: Programming Language :: Python :: 3
Classifier: Programming Language :: Python :: 3.10
Classifier: Programming Language :: Python :: 3.11
Classifier: Programming Language :: Python :: 3.12
Requires-Python: >=3.10
License-File: LICENSE
Requires-Dist: httpx>=0.24.0
Requires-Dist: sqlalchemy>=2.0.0
Requires-Dist: pydantic>=2.0.0
Requires-Dist: pydantic-settings>=2.0.0
Requires-Dist: pyyaml>=6.0.1
Requires-Dist: rich>=13.5.0
Requires-Dist: structlog>=23.1.0
Requires-Dist: click>=8.1.0
Requires-Dist: tenacity>=8.2.0
Requires-Dist: anthropic>=0.18.0
Provides-Extra: dev
Requires-Dist: pytest>=7.4.0; extra == "dev"
Requires-Dist: pytest-asyncio>=0.21.0; extra == "dev"
Requires-Dist: pytest-cov>=4.1.0; extra == "dev"
Requires-Dist: black>=23.7.0; extra == "dev"
Requires-Dist: flake8>=6.1.0; extra == "dev"
Requires-Dist: mypy>=1.5.0; extra == "dev"
Requires-Dist: isort>=5.12.0; extra == "dev"
Dynamic: license-file
Dynamic: requires-python
